induslabs/__init__.py
induslabs/client.py
tests/__init__.py
tests/test_stt.py
tests/test_tts.py
induslabs-0.0.12.dist-info/METADATA
induslabs-0.0.12.dist-info/WHEEL
induslabs-0.0.12.dist-info/top_level.txt
induslabs-0.0.12.dist-info/RECORD
