Metadata-Version: 2.4
Name: induslabs
Version: 0.0.12
Summary: Python SDK for IndusLabs Voice API - Text-to-Speech and Speech-to-Text
Home-page: https://github.com/INDUS-AI-DEV/induslabs-python
Author: IndusLabs
Author-email: IndusLabs <support@induslabs.io>
License: MIT
Project-URL: Homepage, https://induslabs.io
Project-URL: Documentation, https://docs.induslabs.io
Project-URL: Repository, https://github.com/INDUS-AI-DEV/induslabs-python
Project-URL: Issues, https://github.com/INDUS-AI-DEV/induslabs-python/issues
Keywords: tts,stt,speech-to-text,text-to-speech,voice-api,audio,indian-languages
Classifier: Development Status :: 3 - Alpha
Classifier: Intended Audience :: Developers
Classifier: Topic :: Software Development :: Libraries :: Python Modules
Classifier: Topic :: Multimedia :: Sound/Audio :: Speech
Classifier: License :: OSI Approved :: MIT License
Classifier: Programming Language :: Python :: 3
Classifier: Programming Language :: Python :: 3.8
Classifier: Programming Language :: Python :: 3.9
Classifier: Programming Language :: Python :: 3.10
Classifier: Programming Language :: Python :: 3.11
Classifier: Programming Language :: Python :: 3.12
Requires-Python: >=3.8
Requires-Dist: requests>=2.25.0
Requires-Dist: aiohttp>=3.8.0
Requires-Dist: websocket-client>=1.7.0
Requires-Dist: numpy>=1.24.0
Requires-Dist: soundfile>=0.12.1
Provides-Extra: dev
Requires-Dist: pytest>=7.0.0; extra == "dev"
Requires-Dist: pytest-asyncio>=0.21.0; extra == "dev"
Requires-Dist: black>=22.0.0; extra == "dev"
Requires-Dist: flake8>=4.0.0; extra == "dev"
Requires-Dist: mypy>=0.950; extra == "dev"
Dynamic: author
Dynamic: home-page
Dynamic: requires-python
